wingpy/__init__.py
wingpy/base.py
wingpy/exceptions.py
wingpy/interfaces.py
wingpy/logger.py
wingpy/scheduling.py
wingpy/cisco/__init__.py
wingpy/cisco/apic.py
wingpy/cisco/catalystcenter.py
wingpy/cisco/cml.py
wingpy/cisco/fmc.py
wingpy/cisco/hyperfabric.py
wingpy/cisco/ise.py
wingpy/cisco/merakidashboard.py
wingpy/cisco/nexusdashboard.py
wingpy/cisco/vmanage.py
wingpy/generic/__init__.py
wingpy/generic/generic.py
wingpy/nsot/__init__.py
wingpy/nsot/nautobot.py
wingpy/nsot/netbox.py
wingpy-1.5.1.dist-info/METADATA
wingpy-1.5.1.dist-info/WHEEL
wingpy-1.5.1.dist-info/licenses/AUTHORS
wingpy-1.5.1.dist-info/licenses/LICENSE
wingpy-1.5.1.dist-info/licenses/NOTICE
wingpy-1.5.1.dist-info/RECORD
