Metadata-Version: 2.4
Name: wingpy
Version: 1.5.1
Summary: API client library built for network engineers.
Project-URL: Repository, https://github.com/wingmendk/wingpy
Project-URL: Documentation, https://wingpy.automation.wingmen.dk
Project-URL: Homepage, https://www.wingmen.dk/en/home-page/
Project-URL: Issues, https://github.com/wingmendk/wingpy/issues
Author: Wingmen Solutions ApS, Andreas Baekdahl, Emil Bisgaard Commerou
License-Expression: GPL-3.0-or-later
License-File: AUTHORS
License-File: LICENSE
License-File: NOTICE
Keywords: ACI,APIC,Cisco,DevNet,FMC,Firepower,Hyperfabric,Network Automation,REST,REST API,RESTAPI,RESTful API
Classifier: Development Status :: 5 - Production/Stable
Classifier: Intended Audience :: Developers
Classifier: License :: OSI Approved :: GNU General Public License v3 or later (GPLv3+)
Classifier: Operating System :: OS Independent
Classifier: Programming Language :: Python
Classifier: Programming Language :: Python :: 3 :: Only
Classifier: Programming Language :: Python :: 3.10
Classifier: Programming Language :: Python :: 3.11
Classifier: Programming Language :: Python :: 3.12
Classifier: Programming Language :: Python :: 3.13
Classifier: Programming Language :: Python :: 3.14
Classifier: Topic :: Software Development :: Libraries
Classifier: Topic :: System :: Networking
Requires-Python: <3.15,>=3.10
Requires-Dist: arrow>=1.3.0
Requires-Dist: httpx[socks]>=0.28.1
Requires-Dist: loguru>=0.7.3
Requires-Dist: lxml>=5.3.2
Requires-Dist: packaging>=24.2
Requires-Dist: rich>=13.9.4
